data_info/__init__.py
data_info/info.py
preprocessing/__init__.py
preprocessing/categorical.py
preprocessing/exception.py
preprocessing/filtering.py
preprocessing/groupby.py
preprocessing/missing_value.py
preprocessing/outlier.py
preprocessing/preproc_manager.py
preprocessing/preproc_utils.py
preprocessing/replace_value.py
preprocessing/scaler.py
preprocessing/test/__init__.py
preprocessing/test/history_example.py
preproc-23.2.13.dist-info/METADATA
preproc-23.2.13.dist-info/WHEEL
preproc-23.2.13.dist-info/top_level.txt
preproc-23.2.13.dist-info/RECORD
