Metadata-Version: 2.1
Name: preproc
Version: 23.2.13
Summary: 23.02.13 import 경로 수정
Home-page: https://github.com/Neuralworks-io
Author: UNKNOWN
Author-email: UNKNOWN
License: UNKNOWN
Download-URL: https://github.com/Neuralworks-io/archive/0.0.tar.gz
Platform: UNKNOWN
